pytest_flakiness/__init__.py
pytest_flakiness/flakiness_report.py
pytest_flakiness/git.py
pytest_flakiness/plugin.py
pytest_flakiness/py.typed
pytest_flakiness/reporter.py
pytest_flakiness/uploader.py
pytest_flakiness-0.12.0.dist-info/WHEEL
pytest_flakiness-0.12.0.dist-info/entry_points.txt
pytest_flakiness-0.12.0.dist-info/METADATA
pytest_flakiness-0.12.0.dist-info/RECORD
