Metadata-Version: 2.3
Name: pytest-flakiness
Version: 0.12.0
Summary: Pytest reporter for Flakiness.io
Author: Andrey Lushnikov
Author-email: Andrey Lushnikov <aslushnikov@gmail.com>
Requires-Dist: brotli>=1.2.0
Requires-Dist: pytest>=9.0.2
Requires-Dist: requests>=2.32.5
Requires-Python: >=3.13
